du/random_utils.py
du/__init__.py
du/utils.py
du/trial.py
du/performance_utils.py
du/timer_utils.py
du/io_utils.py
du/walk_utils.py
du/theano_utils.py
du/image_processing.py
du/joblib_utils.py
du/numpy_utils.py
du/_test_utils.py
du/cv2_utils.py
du/dicom_utils.py
du/yaml_db.py
du/unsupervised/__init__.py
du/unsupervised/sparse_filtering.py
du/sandbox/__init__.py
du/sandbox/shm_utils.py
du/sandbox/visualization.py
du/sandbox/localization_utils.py
du/sandbox/auc_var.py
du/sandbox/summary.py
du/sandbox/tta_utils.py
du/sandbox/fcn_utils.py
du/sandbox/hyperopt_trial.py
du/sandbox/hyperopt_utils.py
du/sandbox/plot_ascii.py
du/sandbox/fisher_vector.py
du/sandbox/interactive_utils.py
du/sandbox/treeano_trial_utils.py
du/sandbox/plot_training_curves.py
du/sandbox/uncategorized.py
du/sandbox/decorator_utils.py
du/sandbox/tests/__init__.py
du/sandbox/tests/fcn_utils_test.py
du/sandbox/tests/summary_test.py
du/sandbox/tests/fisher_vector_test.py
du/sandbox/tests/hyperopt_utils_test.py
du/parallel/__init__.py
du/parallel/buffering.py
du/parallel/multiprocessing_generator.py
du/parallel/tests/__init__.py
du/parallel/tests/multiprocessing_generator_test.py
du/model/__init__.py
du/model/_ExtraTreesRegressorEmbedding.py
du/model/_WeightedLogisticRegression.py
du/model/_ExtraTreesFeatureSelectionClassifier.py
du/preprocessing/__init__.py
du/preprocessing/image.py
du/preprocessing/image2d.py
du/preprocessing/threshold_standard_scaler.py
du/preprocessing/tests/__init__.py
du/preprocessing/tests/image2d_test.py
du/preprocessing/tests/image_test.py
du/dataset/__init__.py
du/dataset/patterns.py
du/dataset/higher_order.py
du/dataset/base.py
du/dataset/constructors.py
du/dataset/extras.py
du/dataset/dsl.py
du/dataset/tests/__init__.py
du/dataset/tests/patterns_test.py
du/dataset/tests/extras_test.py
du/dataset/tests/dataset_test.py
du/tests/__init__.py
du/tests/trial_test.py
du/tests/utils_test.py
du-0.0.1.dev0.dist-info/metadata.json
du-0.0.1.dev0.dist-info/DESCRIPTION.rst
du-0.0.1.dev0.dist-info/top_level.txt
du-0.0.1.dev0.dist-info/METADATA
du-0.0.1.dev0.dist-info/RECORD
du-0.0.1.dev0.dist-info/WHEEL
